drommage/__init__.py
drommage/cli.py
drommage/core/__init__.py
drommage/core/analysis.py
drommage/core/analysis_queue.py
drommage/core/cache.py
drommage/core/config_tui.py
drommage/core/diff_tracker.py
drommage/core/engine.py
drommage/core/git_integration.py
drommage/core/interface.py
drommage/core/llm_analyzer.py
drommage/core/pattern_analyzer.py
drommage/core/prompts.py
drommage/core/providers.py
drommage/core/region_analyzer.py
drommage-1.0.4.dist-info/licenses/LICENSE
drommage-1.0.4.dist-info/METADATA
drommage-1.0.4.dist-info/WHEEL
drommage-1.0.4.dist-info/entry_points.txt
drommage-1.0.4.dist-info/top_level.txt
drommage-1.0.4.dist-info/RECORD
