Metadata-Version: 2.4
Name: drommage
Version: 1.0.4
Summary: AI-powered git commit analysis tool for developers and teams
Author-email: Zhaxybayev Daulet <damelimm@gmail.com>
License: MIT
Project-URL: Homepage, https://github.com/yoursteacup/DRommage
Project-URL: Repository, https://github.com/yoursteacup/DRommage
Project-URL: Documentation, https://github.com/yoursteacup/DRommage#readme
Project-URL: Issues, https://github.com/yoursteacup/DRommage/issues
Keywords: git,llm,ai,analysis,commit,retrospection,code-review,cli,tui
Classifier: Development Status :: 5 - Production/Stable
Classifier: Intended Audience :: Developers
Classifier: License :: OSI Approved :: MIT License
Classifier: Programming Language :: Python :: 3
Classifier: Programming Language :: Python :: 3.8
Classifier: Programming Language :: Python :: 3.9
Classifier: Programming Language :: Python :: 3.10
Classifier: Programming Language :: Python :: 3.11
Classifier: Programming Language :: Python :: 3.12
Classifier: Topic :: Software Development :: Version Control :: Git
Classifier: Topic :: Software Development :: Quality Assurance
Classifier: Environment :: Console :: Curses
Classifier: Environment :: Console
Requires-Python: >=3.8
License-File: LICENSE
Provides-Extra: dev
Requires-Dist: pytest; extra == "dev"
Requires-Dist: flake8; extra == "dev"
Requires-Dist: mypy; extra == "dev"
Dynamic: license-file
